zmq_shell_tools/__init__.py
zmq_shell_tools/cli.py
zmq_shell_tools/main.py
zmq_shell_tools/py.typed
zmq_shell_tools/signal.py
zmq_shell_tools-0.1.0.dist-info/licenses/LICENSE
zmq_shell_tools-0.1.0.dist-info/METADATA
zmq_shell_tools-0.1.0.dist-info/WHEEL
zmq_shell_tools-0.1.0.dist-info/entry_points.txt
zmq_shell_tools-0.1.0.dist-info/top_level.txt
zmq_shell_tools-0.1.0.dist-info/RECORD
