Metadata-Version: 2.4
Name: zmq-shell-tools
Version: 0.1.0
Summary: ZeroMQ sockets for the command line
Author-email: Jakob Zahn <jakob.zahn@mailbox.org>
Maintainer-email: Jakob Zahn <jakob.zahn@mailbox.org>
License-Expression: AGPL-3.0-only
Project-URL: source, https://codeberg.org/jbdyn/zmq-shell-tools-python
Project-URL: documentation, https://codeberg.org/jbdyn/zmq-shell-tools-python/wiki
Project-URL: issues, https://codeberg.org/jbdyn/zmq-shell-tools-python/issues
Project-URL: changelog, https://codeberg.org/jbdyn/zmq-shell-tools-python/src/branch/main/CHANGELOG.md
Keywords: zeromq,zmq,0mq,message queue,decentral,sockets,cli,ci/cd,continuous integration,container,pipeline,pubsub,reqrep,network,architecture
Classifier: Programming Language :: Python :: 3
Classifier: Programming Language :: Python :: 3.12
Classifier: Programming Language :: Python :: 3.13
Classifier: Development Status :: 3 - Alpha
Classifier: Environment :: Console
Classifier: Intended Audience :: Developers
Classifier: Intended Audience :: Education
Classifier: Topic :: Communications
Requires-Python: >=3.12
License-File: LICENSE
Requires-Dist: click
Requires-Dist: loguru
Requires-Dist: pyzmq
Dynamic: license-file
